ecpb/__init__.py
ecpb/ecpb.py
ecpb-1.4.data/scripts/ecpb
ecpb-1.4.dist-info/METADATA
ecpb-1.4.dist-info/WHEEL
ecpb-1.4.dist-info/top_level.txt
ecpb-1.4.dist-info/RECORD
