Metadata-Version: 2.1
Name: ecpb
Version: 1.4
Summary: Upload code and get into your clipboard
Home-page: https://github.com/hugonxc/ecpb
Author: Hugo Neves de Carvalho
Author-email: hugonvsc@gmail.com
License: UNKNOWN
Platform: UNKNOWN
Classifier: Programming Language :: Python :: 3
Classifier: License :: OSI Approved :: MIT License
Classifier: Operating System :: OS Independent
Requires-Dist: clipboard
Requires-Dist: requests
